mkpipe_extractor_postgres/__init__.py
mkpipe_extractor_postgres/registry_jar.py
mkpipe_extractor_postgres/jars/mysql-connector-j-9.1.0.jar
mkpipe_extractor_postgres/jars/oci-java-sdk-common-3.41.2.jar
mkpipe_extractor_postgres/jars/org.postgresql_postgresql-42.7.4.jar
mkpipe_extractor_postgres/jars/protobuf-java-4.26.1.jar
mkpipe_extractor_postgres-0.2.4.dist-info/licenses/LICENSE
mkpipe_extractor_postgres-0.2.4.dist-info/METADATA
mkpipe_extractor_postgres-0.2.4.dist-info/WHEEL
mkpipe_extractor_postgres-0.2.4.dist-info/entry_points.txt
mkpipe_extractor_postgres-0.2.4.dist-info/top_level.txt
mkpipe_extractor_postgres-0.2.4.dist-info/RECORD
